clocklogger/__init__.py
clocklogger/analysis.py
clocklogger/input.py
clocklogger/logger.py
clocklogger/weatherlogger.py
clocklogger/output/__init__.py
clocklogger/output/influxdb.py
clocklogger/output/tempodb.py
clocklogger/output/textfile.py
clocklogger/source/__init__.py
clocklogger/source/weather.py
clocklogger-0.2.2.dist-info/entry_points.txt
clocklogger-0.2.2.dist-info/WHEEL
clocklogger-0.2.2.dist-info/METADATA
clocklogger-0.2.2.dist-info/RECORD
