Metadata-Version: 1.2
Name: clocklogger
Version: 0.2.2
Summary: Clock and weather logger
Home-page: https://github.com/ricklupton/clocklogger
License: UNKNOWN
Author: Rick Lupton
Author-email: mail@ricklupton.name
Classifier: License :: OSI Approved :: MIT License
